Workbook

Sheet Datos
A1: Fecha | B1: Mes | C1: Categoría | D1: Descripción | E1: Monto (COP) | G1: Nota
A2: 45962 | B2: =DATE(YEAR(A2),MONTH(A2),1) -> 45962 | C2: Vivienda | D2: Arriendo | E2: 900000 | G2: Datos de ejemplo creados para este proyecto (azul = valores ingresados). Reemplázalos por tus gastos reales si quieres.
A3: 45964 | B3: =DATE(YEAR(A3),MONTH(A3),1) -> 45962 | C3: Alimentación | D3: Mercado del mes | E3: 358000
A4: 45973 | B4: =DATE(YEAR(A4),MONTH(A4),1) -> 45962 | C4: Alimentación | D4: Restaurantes y domicilios | E4: 166000
A5: 45969 | B5: =DATE(YEAR(A5),MONTH(A5),1) -> 45962 | C5: Transporte | D5: Transporte y gasolina | E5: 154000
A6: 45976 | B6: =DATE(YEAR(A6),MONTH(A6),1) -> 45962 | C6: Servicios | D6: Servicios públicos e internet | E6: 201000
A7: 45981 | B7: =DATE(YEAR(A7),MONTH(A7),1) -> 45962 | C7: Entretenimiento | D7: Salidas y suscripciones | E7: 125000
A8: 45983 | B8: =DATE(YEAR(A8),MONTH(A8),1) -> 45962 | C8: Salud | D8: Salud y bienestar | E8: 93000
A9: 45986 | B9: =DATE(YEAR(A9),MONTH(A9),1) -> 45962 | C9: Educación | D9: Materiales y cursos | E9: 106000
A10: 45992 | B10: =DATE(YEAR(A10),MONTH(A10),1) -> 45992 | C10: Vivienda | D10: Arriendo | E10: 900000
A11: 45994 | B11: =DATE(YEAR(A11),MONTH(A11),1) -> 45992 | C11: Alimentación | D11: Mercado del mes | E11: 430000
A12: 46003 | B12: =DATE(YEAR(A12),MONTH(A12),1) -> 45992 | C12: Alimentación | D12: Restaurantes y domicilios | E12: 234000
A13: 45999 | B13: =DATE(YEAR(A13),MONTH(A13),1) -> 45992 | C13: Transporte | D13: Transporte y gasolina | E13: 150000
A14: 46006 | B14: =DATE(YEAR(A14),MONTH(A14),1) -> 45992 | C14: Servicios | D14: Servicios públicos e internet | E14: 203000
... A97: 46320 | B97: =DATE(YEAR(A97),MONTH(A97),1) -> 46296 | C97: Educación | D97: Materiales y cursos | E97: 120000

Sheet Resumen
A1: Resumen de gastos personales (COP)
A3: Mes | B3: Gasto real | C3: Proyección | D3: Índice | F3: Categoría | G3: Total 12 meses | H3: % del total
A4: =DATE(2025,11,1) -> 45962 | B4: =SUMIFS(Datos!$E$2:$E$97,Datos!$B$2:$B$97,A4) -> 2103000 | D4: 1 | F4: Vivienda | G4: =SUMIFS(Datos!$E$2:$E$97,Datos!$C$2:$C$97,F4) -> 11250000 | H4: =G4/SUM($G$4:$G$10) -> 0.41902563
A5: =DATE(2025,12,1) -> 45992 | B5: =SUMIFS(Datos!$E$2:$E$97,Datos!$B$2:$B$97,A5) -> 2255000 | D5: 2 | F5: Alimentación | G5: =SUMIFS(Datos!$E$2:$E$97,Datos!$C$2:$C$97,F5) -> 6915000 | H5: =G5/SUM($G$4:$G$10) -> 0.25756108
A6: =DATE(2026,1,1) -> 46023 | B6: =SUMIFS(Datos!$E$2:$E$97,Datos!$B$2:$B$97,A6) -> 2194000 | D6: 3 | F6: Transporte | G6: =SUMIFS(Datos!$E$2:$E$97,Datos!$C$2:$C$97,F6) -> 2007000 | H6: =G6/SUM($G$4:$G$10) -> 0.074754172
A7: =DATE(2026,2,1) -> 46054 | B7: =SUMIFS(Datos!$E$2:$E$97,Datos!$B$2:$B$97,A7) -> 2196000 | D7: 4 | F7: Servicios | G7: =SUMIFS(Datos!$E$2:$E$97,Datos!$C$2:$C$97,F7) -> 2669000 | H7: =G7/SUM($G$4:$G$10) -> 0.099411502
A8: =DATE(2026,3,1) -> 46082 | B8: =SUMIFS(Datos!$E$2:$E$97,Datos!$B$2:$B$97,A8) -> 2258000 | D8: 5 | F8: Entretenimiento | G8: =SUMIFS(Datos!$E$2:$E$97,Datos!$C$2:$C$97,F8) -> 1581000 | H8: =G8/SUM($G$4:$G$10) -> 0.058887068
A9: =DATE(2026,4,1) -> 46113 | B9: =SUMIFS(Datos!$E$2:$E$97,Datos!$B$2:$B$97,A9) -> 2254000 | D9: 6 | F9: Salud | G9: =SUMIFS(Datos!$E$2:$E$97,Datos!$C$2:$C$97,F9) -> 1142000 | H9: =G9/SUM($G$4:$G$10) -> 0.042535757
A10: =DATE(2026,5,1) -> 46143 | B10: =SUMIFS(Datos!$E$2:$E$97,Datos!$B$2:$B$97,A10) -> 2188000 | D10: 7 | F10: Educación | G10: =SUMIFS(Datos!$E$2:$E$97,Datos!$C$2:$C$97,F10) -> 1284000 | H10: =G10/SUM($G$4:$G$10) -> 0.047824791
A11: =DATE(2026,6,1) -> 46174 | B11: =SUMIFS(Datos!$E$2:$E$97,Datos!$B$2:$B$97,A11) -> 2240000 | D11: 8 | F11: Total | G11: =SUM(G4:G10) -> 26848000
A12: =DATE(2026,7,1) -> 46204 | B12: =SUMIFS(Datos!$E$2:$E$97,Datos!$B$2:$B$97,A12) -> 2259000 | D12: 9
A13: =DATE(2026,8,1) -> 46235 | B13: =SUMIFS(Datos!$E$2:$E$97,Datos!$B$2:$B$97,A13) -> 2289000 | D13: 10
A14: =DATE(2026,9,1) -> 46266 | B14: =SUMIFS(Datos!$E$2:$E$97,Datos!$B$2:$B$97,A14) -> 2309000 | D14: 11
A15: =DATE(2026,10,1) -> 46296 | B15: =SUMIFS(Datos!$E$2:$E$97,Datos!$B$2:$B$97,A15) -> 2303000 | C15: =B15 -> 2303000 | D15: 12
A16: =DATE(YEAR(A15),MONTH(A15)+1,1) -> 46327 | C16: =ROUND(FORECAST(D16,$B$4:$B$15,$D$4:$D$15),0) -> 2317924 | D16: 13
A17: =DATE(YEAR(A16),MONTH(A16)+1,1) -> 46357 | C17: =ROUND(FORECAST(D17,$B$4:$B$15,$D$4:$D$15),0) -> 2330323 | D17: 14
A18: =DATE(YEAR(A17),MONTH(A17)+1,1) -> 46388 | C18: =ROUND(FORECAST(D18,$B$4:$B$15,$D$4:$D$15),0) -> 2342721 | D18: 15
A19: Meses 13-15 = proyección con tendencia lineal (función FORECAST).
A22: Pregunta clave: ¿En qué mes se proyecta el mayor gasto y en qué categoría gasto más?
A23: Mes con mayor gasto proyectado (próx. 3 meses) | E23: =INDEX(A16:A18,MATCH(MAX(C16:C18),C16:C18,0)) -> 46388
A24: Gasto proyectado en ese mes | E24: =MAX(C16:C18) -> 2342721
A25: Categoría donde más gasto | E25: =INDEX(F4:F10,MATCH(MAX(G4:G10),G4:G10,0)) -> Vivienda
A26: Promedio mensual real | E26: =AVERAGE(B4:B15) -> 2237333.3
A27: Mes real con mayor gasto | E27: =INDEX(A4:A15,MATCH(MAX(B4:B15),B4:B15,0)) -> 46266

Sheet Interpretación
A1: Interpretación de resultados
A3: Pregunta clave
A4: ¿En qué mes se proyecta el mayor gasto personal y en qué categoría se concentra el dinero?
A6: Respuestas (calculadas con fórmulas en la hoja Resumen)
A7: ="Mes con mayor gasto proyectado: "&CHOOSE(MONTH(Resumen!E23),"enero","febrero","marzo","abril","mayo","junio","julio","agosto","septiembre","octubre","noviembre","diciembre")&" "&YEAR(Resumen!E23)&" (aprox. $"&TEXT(Resumen!E24,"#,##0")&" COP)." -> Mes con mayor gasto proyectado: enero 2027 (aprox. $2,342,721 COP).
A8: ="Categoría con más gasto: "&Resumen!E25&" ("&TEXT(MAX(Resumen!H4:H10),"0.0%")&" del total de 12 meses)." -> Categoría con más gasto: Vivienda (41.9% del total de 12 meses).
A9: ="Promedio mensual real: $"&TEXT(Resumen!E26,"#,##0")&" COP." -> Promedio mensual real: $2,237,333 COP.
A11: Lectura
A12: • La línea de tendencia muestra que el gasto mensual sube de forma gradual; la proyección continúa esa tendencia, por eso el último mes proyectado es el más alto.
A13: • La vivienda (arriendo) es el gasto fijo más grande; Alimentación es el gasto más variable y el que más conviene vigilar.
A14: • Diciembre sube frente a noviembre y enero por mayor gasto en comida y entretenimiento: conviene planear un presupuesto especial para esa época.
A15: • Limitación: la proyección es una tendencia lineal simple sobre 12 meses; sirve como guía, no como predicción exacta.
A16: • Acción sugerida: fijar un tope mensual para Alimentación y Entretenimiento y revisar el resumen cada mes.

Sheet Documentación
A1: Documentación del proyecto
A3: Tema elegido | B3: Control de gastos personales: análisis de 12 meses (nov-2025 a oct-2026) y proyección de los próximos 3 meses.
A4: Pregunta clave | B4: ¿En qué mes se proyecta el mayor gasto y en qué categoría gasto más?
A5: Fuente de datos | B5: Datos de ejemplo creados por el autor para este proyecto (96 filas, 8 gastos por mes, en pesos colombianos). No son datos bancarios reales.
A6: Funciones y herramientas | B6: SUMIFS (totales por mes y categoría), FORECAST (proyección lineal), INDEX/MATCH (respuestas), gráficos de línea y barras. Con IA de Excel: Ideas (Inicio → Ideas), hoja de pronóstico (Datos → Hoja de previsión) y gráficos recomendados (Insertar → Gráficos recomendados). [Completa aquí qué sugirió Ideas en tu Excel.]
A7: Conclusiones | B7: El gasto sube gradualmente mes a mes; el mayor gasto proyectado cae en el último mes del pronóstico; Vivienda y Alimentación concentran la mayor parte del dinero; diciembre sube por gasto en comida y entretenimiento. Detalle en la hoja Interpretación.
A8: Hojas del archivo | B8: Datos · Resumen · Interpretación · Documentación
